AUTHORS.rst
CONTRIBUTING.rst
HISTORY.rst
LICENSE
MANIFEST.in
README.rst
setup.cfg
setup.py
docs/Makefile
docs/authors.rst
docs/conf.py
docs/contributing.rst
docs/history.rst
docs/index.rst
docs/installation.rst
docs/make.bat
docs/readme.rst
docs/usage.rst
fake_tree/__init__.py
fake_tree/cli.py
fake_tree/fake_tree.py
fake_tree.egg-info/PKG-INFO
fake_tree.egg-info/SOURCES.txt
fake_tree.egg-info/dependency_links.txt
fake_tree.egg-info/entry_points.txt
fake_tree.egg-info/not-zip-safe
fake_tree.egg-info/requires.txt
fake_tree.egg-info/top_level.txt
tests/__init__.py
tests/test_fake_tree.py