Metadata-Version: 1.2
Name: fake-tree
Version: 0.0.1
Summary: Fake Tree creates a fake directory tree and files with no content to practice manipulating files.
Home-page: https://github.com/hungntgrb/fake_tree
Author: Hung Nguyen Thanh
Author-email: hungnt89@gmail.com
License: MIT license
Keywords: fake_tree
Platform: UNKNOWN
Classifier: Development Status :: 2 - Pre-Alpha
Classifier: Intended Audience :: Developers
Classifier: License :: OSI Approved :: MIT License
Classifier: Natural Language :: English
Classifier: Programming Language :: Python :: 3
Classifier: Programming Language :: Python :: 3.6
Classifier: Programming Language :: Python :: 3.7
Classifier: Programming Language :: Python :: 3.8
Requires-Python: >=3.6
